.gitignore
HISTORY.rst
LICENSE.txt
README.md
setup.py
ooldap/__init__.py
ooldap/foundation.py
ooldap.egg-info/PKG-INFO
ooldap.egg-info/SOURCES.txt
ooldap.egg-info/dependency_links.txt
ooldap.egg-info/top_level.txt
ooldap/objects/__init__.py