Metadata-Version: 1.0
Name: ooldap
Version: 0.1.0
Summary: Object Oriented LDAP
Home-page: http://github.com/TAMUArch/ooldap
Author: John
Author-email: johnphillips@arch.tamu.edu
License: Apache License 2.0
Platform: UNKNOWN
